{
  "version": "0.2",
  "ignorePaths": ["web/"],
  "dictionaryDefinitions": [],
  "dictionaries": [],
  "words": [
    "AUTOINCREMENT",
    "CDPATH",
    "Celeron",
    "ENOSYS",
    "Emby",
    "Geminilake",
    "HEALTHCHECK",
    "Ironman",
    "Jellyfin",
    "Kodi",
    "NEWGROUP",
    "PGID",
    "PUID",
    "Prereq",
    "Qube",
    "Radarr",
    "Razzle",
    "SARIF",
    "Shawshank",
    "Sonarr",
    "TMDB",
    "Turso",
    "affordances",
    "autobrr",
    "bluray",
    "bunx",
    "cesarnml",
    "coderabbit",
    "coderabbitai",
    "dismissable",
    "emptively",
    "eztv",
    "footgun",
    "gatekeeping",
    "gluetun",
    "greptile",
    "hostnames",
    "idempotently",
    "infohash",
    "mktemp",
    "oklch",
    "overengineering",
    "parsererror",
    "precedented",
    "println",
    "qodo",
    "queueable",
    "reparsing",
    "respawn",
    "retarget",
    "retryability",
    "sabaai",
    "scriptable",
    "shadcn",
    "sonarcloud",
    "sonarqube",
    "sonarqubecloud",
    "statx",
    "syncstatewithplan",
    "syscall",
    "tmdb",
    "unbootstrapped",
    "unconfigured",
    "unreachability",
    "unvalidated",
    "upserted",
    "upserts",
    "viewports",
    "watchlist",
    "worktree",
    "worktrees",
    "writeability"
  ],
  "ignoreWords": [],
  "import": []
}
